pdfoe/__init__.py
pdfoe/common.py
pdfoe/gui_pyside_qml.py
pdfoe/gui_tkinter.py
pdfoe/main.py
pdfoe/main.qml
pdfoe/pdf_obj.py
pdf_outline_edit-24.2.3.dist-info/METADATA
pdf_outline_edit-24.2.3.dist-info/WHEEL
pdf_outline_edit-24.2.3.dist-info/entry_points.txt
pdf_outline_edit-24.2.3.dist-info/top_level.txt
pdf_outline_edit-24.2.3.dist-info/RECORD
