Metadata-Version: 2.1
Name: pdf-outline-edit
Version: 24.2.3
Summary: Mini PDF outline editor
Author-email: slbtty <shenlebantongying@gmail.com>
Classifier: Programming Language :: Python :: 3
Requires-Python: >=3.11
Requires-Dist: pymupdf
Provides-Extra: qt
Requires-Dist: PySide6-Essentials >=6.6 ; extra == 'qt'
